eedl/__init__.py
eedl/core.py
eedl/google_cloud.py
eedl/helpers.py
eedl/image.py
eedl/merge.py
eedl/mosaic_rasters.py
eedl/zonal.py
eedl-2023.9.25.dist-info/METADATA
eedl-2023.9.25.dist-info/WHEEL
eedl-2023.9.25.dist-info/top_level.txt
eedl-2023.9.25.dist-info/RECORD
