Metadata-Version: 2.1
Name: eedl
Version: 2023.9.25
Summary: Code to export arbitrarily large areas of data from Earth Engine to local storage and optionally process data locally afterward
Home-page: https://github.com/water3d/eedl
Author: nickrsan, AdamJCrawford
Platform: unix
Platform: linux
Platform: osx
Platform: cygwin
Platform: win32
Classifier: Programming Language :: Python :: 3
Classifier: Programming Language :: Python :: 3 :: Only
Classifier: Programming Language :: Python :: 3.8
Classifier: Programming Language :: Python :: 3.9
Classifier: Programming Language :: Python :: 3.10
Classifier: Programming Language :: Python :: 3.11
Requires-Python: >=3.8
Requires-Dist: gdal
Requires-Dist: rasterstats
Requires-Dist: earthengine-api
Requires-Dist: fiona
Requires-Dist: pandas
Requires-Dist: seaborn >=0.12.0
Requires-Dist: google-cloud-storage
Requires-Dist: setuptools
Requires-Dist: requests
Requires-Dist: pytest
Requires-Dist: typing-extensions
